LICENSE
MANIFEST.in
README.rst
VERSION
requirements-dev.txt
requirements.txt
setup.cfg
setup.py
garelay/__init__.py
garelay/celery.py
garelay/tasks.py
garelay/urls.py
garelay/views.py
garelay/wsgi.py
garelay.egg-info/PKG-INFO
garelay.egg-info/SOURCES.txt
garelay.egg-info/dependency_links.txt
garelay.egg-info/not-zip-safe
garelay.egg-info/requires.txt
garelay.egg-info/top_level.txt
garelay/management/__init__.py
garelay/management/commands/__init__.py
garelay/management/commands/register_events.py
garelay/management/commands/relay_events.py
garelay/server/__init__.py
garelay/server/settings.py
garelay/server/tasks.py
garelay/server/urls.py
garelay/server/views.py
garelay/server/tests/__init__.py
garelay/server/tests/test_tasks.py
garelay/server/tests/test_views.py
garelay/settings/__init__.py
garelay/settings/base.py
garelay/settings/dev.py
garelay/settings/production.py
garelay/tests/__init__.py
garelay/tests/test_commands.py
garelay/tests/test_tasks.py
garelay/tracker/__init__.py
garelay/tracker/models.py
garelay/tracker/settings.py
garelay/tracker/tasks.py
garelay/tracker/urls.py
garelay/tracker/views.py
garelay/tracker/migrations/0001_initial.py
garelay/tracker/migrations/0002_auto_20151003_2114.py
garelay/tracker/migrations/__init__.py
garelay/tracker/tests/__init__.py
garelay/tracker/tests/test_models.py
garelay/tracker/tests/test_tasks.py
garelay/tracker/tests/test_views.py